{
  "icon_usefulness": 9,
  "discard": false,
  "visual_concepts": [
    "airplane",
    "flight",
    "aviation",
    "travel",
    "transportation",
    "aerospace",
    "journey",
    "vacation",
    "departure",
    "transit"
  ],
  "task_intents": [
    "travel planning",
    "booking flights",
    "business trips",
    "vacation preparation",
    "logistics coordination",
    "airport transit",
    "international travel",
    "itinerary management",
    "flight status tracking",
    "travel documentation"
  ],
  "example_tasks": [
    "Book flight to Tokyo for conference",
    "Research travel insurance options",
    "Renew passport for upcoming trip",
    "Compare airline ticket prices",
    "Check flight status for departure",
    "Pack luggage for business trip",
    "Arrange airport shuttle service",
    "Confirm hotel reservation in London",
    "Apply for travel visa",
    "Create travel itinerary for summer vacation",
    "Review airline loyalty program benefits",
    "Purchase travel adapters",
    "Coordinate group travel logistics",
    "Download boarding passes",
    "Research local transportation in Paris",
    "Update travel calendar"
  ],
  "poor_matches": [
    "Design new website logo",
    "Review quarterly financial report",
    "Fix bug in login module",
    "Write unit tests for API",
    "Organize office supply closet",
    "Schedule team building lunch",
    "Update database schema"
  ],
  "reasoning": "The airplane icon is a universally recognized symbol for travel and aviation, making it highly effective for categorizing tasks related to trips, logistics, and transit."
}