{
  "icon_usefulness": 4,
  "discard": false,
  "visual_concepts": [
    "I-beam",
    "text cursor",
    "vertical alignment",
    "structural support",
    "column",
    "pillar",
    "capital letter I",
    "serif",
    "typography",
    "text selection",
    "insertion point"
  ],
  "task_intents": [
    "text editing",
    "formatting",
    "copywriting",
    "proofreading",
    "structural organization",
    "alignment",
    "data entry",
    "transcription"
  ],
  "example_tasks": [
    "Edit project proposal draft",
    "Proofread quarterly report",
    "Format technical documentation",
    "Copyedit blog post series",
    "Transcribe meeting notes",
    "Refine email newsletter content",
    "Update website copy",
    "Review manuscript for errors",
    "Draft executive summary",
    "Standardize document formatting",
    "Write documentation for API",
    "Fix typos in user manual",
    "Organize text-based data",
    "Insert missing citations",
    "Adjust paragraph alignment"
  ],
  "poor_matches": [
    "Buy groceries",
    "Schedule dentist appointment",
    "Fix leaking faucet",
    "Call bank regarding loan",
    "Research flight prices",
    "Water the garden",
    "Clean the garage"
  ],
  "reasoning": "The icon strongly resembles a text cursor or I-beam, making it highly suitable for tasks involving writing, editing, or formatting text, but it is too abstract for general task management."
}