{
  "icon_usefulness": 8,
  "discard": false,
  "visual_concepts": [
    "person",
    "user",
    "human",
    "profile",
    "music note",
    "audio",
    "sound",
    "melody",
    "artist",
    "performer",
    "singer",
    "musician",
    "composer"
  ],
  "task_intents": [
    "music composition",
    "audio production",
    "vocal practice",
    "music theory study",
    "instrumental rehearsal",
    "sound design",
    "podcast editing",
    "music library management",
    "performance preparation",
    "audio mixing"
  ],
  "example_tasks": [
    "Compose melody for new project",
    "Practice guitar scales",
    "Edit podcast episode audio",
    "Transcribe piano sheet music",
    "Mix background music tracks",
    "Record vocal performance",
    "Organize digital music library",
    "Study music theory concepts",
    "Prepare setlist for gig",
    "Design sound effects for game",
    "Master final audio track",
    "Collaborate with session musician",
    "Write lyrics for new song",
    "Configure audio interface settings",
    "Research music production software"
  ],
  "poor_matches": [
    "Update user profile settings",
    "Manage team member permissions",
    "Review employee performance",
    "Add new contact to CRM",
    "Schedule meeting with client",
    "Write technical documentation",
    "Analyze database performance"
  ],
  "reasoning": "The combination of a person and a music note creates a strong, specific visual metaphor for creative audio work, making it highly effective for distinguishing music-related tasks from general administrative or personal tasks."
}