{
  "icon_usefulness": 4,
  "discard": false,
  "visual_concepts": [
    "letter A",
    "alphabet",
    "typography",
    "text label",
    "initial",
    "classification",
    "categorization",
    "tagging",
    "indexing",
    "sorting",
    "priority level",
    "academic grade"
  ],
  "task_intents": [
    "labeling",
    "categorizing",
    "prioritizing",
    "indexing",
    "grading",
    "identifying",
    "naming",
    "grouping"
  ],
  "example_tasks": [
    "Assign priority A to urgent project tasks",
    "Label research papers by author",
    "Categorize incoming emails by project",
    "Grade student assignments",
    "Index documentation by chapter",
    "Tag meeting notes by department",
    "Sort inventory by category",
    "Mark high-priority action items",
    "Group tasks by urgency level",
    "Assign status codes to support tickets",
    "Label archive folders",
    "Categorize expense reports",
    "Identify key stakeholders",
    "Name new project modules",
    "Organize library by genre"
  ],
  "poor_matches": [
    "Review quarterly budget",
    "Plan summer travel itinerary",
    "Compare cloud GPU providers",
    "Organize photography equipment",
    "Investigate backup strategy",
    "Analyze model evaluation metrics",
    "Prepare conference presentation"
  ],
  "reasoning": "The icon is a generic 'A' character, which is highly abstract. It is best suited for tasks involving labeling, grading, or categorization systems rather than representing a specific physical object or action."
}