{
  "icon_usefulness": 7,
  "discard": false,
  "visual_concepts": [
    "balcony",
    "window",
    "archway",
    "railing",
    "view",
    "building exterior",
    "architecture",
    "terrace",
    "opening",
    "portal"
  ],
  "task_intents": [
    "home improvement",
    "property maintenance",
    "real estate",
    "architecture design",
    "outdoor space planning",
    "building inspection",
    "travel accommodation",
    "facility management"
  ],
  "example_tasks": [
    "Repair balcony railing",
    "Paint apartment window frames",
    "Design terrace seating area",
    "Inspect building facade for cracks",
    "Book hotel room with balcony view",
    "Clean exterior windows",
    "Research balcony safety regulations",
    "Install window security locks",
    "Plan garden terrace landscaping",
    "Review property maintenance schedule",
    "Draft architectural plans for extension",
    "Compare window insulation options",
    "Schedule balcony deep cleaning",
    "Assess structural integrity of terrace",
    "Purchase outdoor furniture for balcony"
  ],
  "poor_matches": [
    "Write weekly status report",
    "Update software dependencies",
    "Send client email",
    "Review quarterly budget",
    "Organize digital files",
    "Attend team meeting",
    "Research marketing strategy"
  ],
  "reasoning": "The icon clearly depicts a balcony or arched window, making it highly suitable for tasks related to home maintenance, property management, or architectural design."
}